create_dara_app/__init__.py
create_dara_app/cli.py
create_dara_app/default_command_group.py
create_dara_app/templates/__init__.py
create_dara_app/templates/default/cookiecutter.json
create_dara_app/templates/default/hooks/post_gen_project.py
create_dara_app/templates/default/hooks/pre_gen_project.py
create_dara_app/templates/default/{{ cookiecutter.__project_slug }}/.gitignore
create_dara_app/templates/default/{{ cookiecutter.__project_slug }}/README.md
create_dara_app/templates/default/{{ cookiecutter.__project_slug }}/poetry.toml
create_dara_app/templates/default/{{ cookiecutter.__project_slug }}/pyproject.toml
create_dara_app/templates/default/{{ cookiecutter.__project_slug }}/ruff.toml
create_dara_app/templates/default/{{ cookiecutter.__project_slug }}/static/dara_light.svg
create_dara_app/templates/default/{{ cookiecutter.__project_slug }}/{{ cookiecutter.__package_name }}/main.py
create_dara_app/templates/default/{{ cookiecutter.__project_slug }}/{{ cookiecutter.__package_name }}/pages/components_page.py
create_dara_app/templates/default/{{ cookiecutter.__project_slug }}/{{ cookiecutter.__package_name }}/pages/intro_page.py
create_dara_app/templates/default/{{ cookiecutter.__project_slug }}/{{ cookiecutter.__package_name }}/utils/components.py
create_dara_app-1.25.1.dist-info/LICENSE
create_dara_app-1.25.1.dist-info/METADATA
create_dara_app-1.25.1.dist-info/WHEEL
create_dara_app-1.25.1.dist-info/entry_points.txt
create_dara_app-1.25.1.dist-info/RECORD
