Metadata-Version: 2.1
Name: create-dara-app
Version: 1.25.1
Summary: CLI to quickly bootstrap a Dara app
Home-page: https://dara.causalens.com/
License: Apache-2.0
Author: Krzysztof Bielikowicz
Author-email: krzysztof@causalens.com
Requires-Python: >=3.10.0,<3.13.0
Classifier: License :: OSI Approved :: Apache Software License
Classifier: Programming Language :: Python :: 3
Classifier: Programming Language :: Python :: 3.10
Classifier: Programming Language :: Python :: 3.11
Classifier: Programming Language :: Python :: 3.12
Requires-Dist: certifi (>=2024.7.4)
Requires-Dist: click (>=8.1.3,<9.0.0)
Requires-Dist: cookiecutter (>=2.1.1,<3.0.0)
Project-URL: Repository, https://github.com/causalens/dara
